{
    "data": [
        {
            "id": "1",
            "Question": "Ques 1",
            "Description": "Desc 1"
        },
        {
            "id": "2",
            "Question": "Ques 1",
            "Description": "Desc 1"
        },
        {
            "id": "3",
            "Question": "Ques 1",
            "Description": "Desc 1"
        },
        {
            "id": "4",
            "Question": "Ques 1",
            "Description": "Desc 1"
        },
        {
            "id": "5",
            "Question": "Ques 1",
            "Description": "Desc 1"
        }
    ]
}